bits_helpers/Makeflow.jnj
bits_helpers/__init__.py
bits_helpers/_version.py
bits_helpers/analytics.py
bits_helpers/args.py
bits_helpers/build.py
bits_helpers/build_template.sh
bits_helpers/clean.py
bits_helpers/cmd.py
bits_helpers/deps.py
bits_helpers/doctor.py
bits_helpers/download.py
bits_helpers/git.py
bits_helpers/init.py
bits_helpers/log.py
bits_helpers/resource_manager.py
bits_helpers/resource_monitor.py
bits_helpers/scheduler.py
bits_helpers/scm.py
bits_helpers/sl.py
bits_helpers/sync.py
bits_helpers/templating_plugin.py
bits_helpers/utilities.py
bits_helpers/workarea.py
bitsorg-0.1.1.data/scripts/bits
bitsorg-0.1.1.data/scripts/bitsBuild
bitsorg-0.1.1.data/scripts/bitsDeps
bitsorg-0.1.1.data/scripts/bitsDoctor
bitsorg-0.1.1.data/scripts/pb
bitsorg-0.1.1.dist-info/licenses/LICENSE.md
debian/changelog
debian/compat
debian/control
debian/copyright
debian/files
debian/rules
docs/SUPPORT
docs/_config.yml
docs/mkdocs.yml
docs/docs/alice_logo.png
docs/docs/deps.png
docs/docs/index.md
docs/docs/quick.md
docs/docs/reference.md
docs/docs/troubleshooting.md
docs/docs/user.md
docs/docs/stylesheets/extra.css
templates/alibuild_to_please.jnj
templates/bits_stack.jnj
tests/package_resources.json
tests/test_analytics.py
tests/test_args.py
tests/test_build.py
tests/test_clean.py
tests/test_cmd.py
tests/test_deepmergedefaults.py
tests/test_defaultswithinclude.py
tests/test_deps.py
tests/test_doctor.py
tests/test_git.py
tests/test_hashing.py
tests/test_init.py
tests/test_log.py
tests/test_packagelist.py
tests/test_parseRecipe.py
tests/test_scheduler.py
tests/test_sync.py
tests/test_utilities.py
tests/test_workarea.py
tests/testdist/broken1.sh
tests/testdist/broken2.sh
tests/testdist/broken3.sh
tests/testdist/broken4.sh
tests/testdist/broken5.sh
tests/testdist/broken6.sh
tests/testdist/broken7.sh
tests/testdist/clobber-initdotsh.sh
tests/testdist/defaults-o2.sh
tests/testdist/defaults-release.sh
tests/testdist/delete-etc.sh
tests/testdist/tracking-env.sh
bitsorg-0.1.1.dist-info/METADATA
bitsorg-0.1.1.dist-info/WHEEL
bitsorg-0.1.1.dist-info/top_level.txt
bitsorg-0.1.1.dist-info/RECORD
