Metadata-Version: 2.4
Name: bitsorg
Version: 0.1.1
Summary: Build Tool
Home-page: https://github.com/bitsorg/bits
Author: Giulio Eulisse
Author-email: Giulio Eulisse <giulio.eulisse@cern.ch>, Timo Wilken <timo.wilken@cern.ch>, Predrag Buncic <predrag.buncic@cern.ch>, Sergio Garcia <sergio.garcia@cern.ch>
Project-URL: homepage, https://github.com/bitsorg/bits
Keywords: HEP,ALICE
Classifier: Development Status :: 5 - Production/Stable
Classifier: Intended Audience :: Developers
Classifier: Topic :: Software Development :: Build Tools
License-File: LICENSE.md
Requires-Dist: pyyaml
Requires-Dist: requests
Requires-Dist: distro
Requires-Dist: jinja2
Requires-Dist: boto3
Provides-Extra: test
Requires-Dist: tox; extra == "test"
Provides-Extra: docs
Requires-Dist: mkdocs; extra == "docs"
Requires-Dist: mkdocs-material; extra == "docs"
Requires-Dist: mkdocs-redirects; extra == "docs"
Dynamic: author
Dynamic: home-page
Dynamic: license-file
